pyfping/__init__.py
pyfping/ping.py
pyfping-1.0.1.dist-info/LICENSE
pyfping-1.0.1.dist-info/METADATA
pyfping-1.0.1.dist-info/WHEEL
pyfping-1.0.1.dist-info/entry_points.txt
pyfping-1.0.1.dist-info/top_level.txt
pyfping-1.0.1.dist-info/RECORD
