Metadata-Version: 2.1
Name: pyfping
Version: 1.0.1
Summary: fping-like python application
Home-page: https://github.com/junka/pyfping
Author: junka
Author-email: wan.junjie@foxmail.com
License: UNKNOWN
Project-URL: Bug Tracker, https://github.com/junka/pyfping/issues
Platform: UNKNOWN
Classifier: Programming Language :: Python :: 3
Classifier: License :: OSI Approved :: BSD License
Requires-Python: >=3.5
License-File: LICENSE
